{
  "posts": [
    {
      "id": "post1",
      "authorId": "62Wv5g3xs",
      "topic": "Topic",
      "content": "Lorem ipsum dolor sit amet, consectetur adipiscing elit. Suspendisse metus erat, semper sit amet ligula in, maximus tincidunt erat. Nulla est tortor, lobortis nec odio in, vestibulum fermentum nulla.",
      "likes": [
        "62Wv5g3xs",
        "7x25RQ2Sl",
        "LQpqWgiZG"
      ],
      "dislikes": [],
      "likesCount": 3,
      "comments": [
        "comment1",
        "HRTObbfft",
        "KdDRIYg19"
      ]
    },
    {
      "id": "Si-SCaMro",
      "authorId": "7x25RQ2Sl",
      "likes": [
        "7x25RQ2Sl",
        "LQpqWgiZG"
      ],
      "dislikes": [],
      "comments": [
        "xXbMpLzog"
      ],
      "likesCount": 2,
      "content": "Donec pretium ipsum non mattis volutpat. Maecenas sed leo a sem porta placerat. Phasellus laoreet egestas nulla, sit amet molestie enim gravida sit amet.",
      "topic": "Web Development"
    },
    {
      "id": "63UJlnSbI",
      "authorId": "LQpqWgiZG",
      "likes": [
        "LQpqWgiZG"
      ],
      "dislikes": [],
      "comments": [],
      "likesCount": 1,
      "content": "Computer Science post",
      "topic": "Computer Science"
    }
  ],
  "comments": [
    {
      "id": "comment1",
      "authorId": "62Wv5g3xs",
      "postId": "post1",
      "parentCommentId": "",
      "content": "Lorem ipsum dolor sit amet, consectetur adipiscing elit. Suspendisse metus erat, semper sit amet ligula in, maximus tincidunt erat. Nulla est tortor, lobortis nec odio in, vestibulum fermentum nulla.",
      "likes": [
        "62Wv5g3xs",
        "LQpqWgiZG"
      ],
      "dislikes": [],
      "likesCount": 2,
      "comments": []
    },
    {
      "authorId": "62Wv5g3xs",
      "comments": [
        "l4Q7Einee"
      ],
      "content": "Lorem ipsum dolor sit amet, consectetur adipiscing elit. Suspendisse metus erat, semper sit amet ligula in, maximus tincidunt erat.",
      "id": "HRTObbfft",
      "likes": [],
      "dislikes": [
        "7x25RQ2Sl",
        "LQpqWgiZG"
      ],
      "likesCount": -2,
      "parentCommentId": null,
      "postId": "post1"
    },
    {
      "authorId": "62Wv5g3xs",
      "comments": [],
      "content": "Lorem ipsum dolor sit amet, consectetur adipiscing elit. Suspendisse metus erat, semper sit amet ligula in, maximus tincidunt erat.",
      "id": "l4Q7Einee",
      "likes": [
        "7x25RQ2Sl"
      ],
      "dislikes": [
        "62Wv5g3xs"
      ],
      "likesCount": 0,
      "parentCommentId": "HRTObbfft",
      "postId": null
    },
    {
      "authorId": "7x25RQ2Sl",
      "comments": [],
      "content": "Komentar",
      "id": "KdDRIYg19",
      "likes": [],
      "dislikes": [],
      "likesCount": 0,
      "parentCommentId": null,
      "postId": "post1"
    },
    {
      "authorId": "7x25RQ2Sl",
      "comments": [
        "TN20NETc1"
      ],
      "content": "Komentar",
      "id": "xXbMpLzog",
      "likes": [
        "7x25RQ2Sl"
      ],
      "dislikes": [],
      "likesCount": 1,
      "parentCommentId": null,
      "postId": "Si-SCaMro"
    },
    {
      "authorId": "7x25RQ2Sl",
      "comments": [],
      "content": "Komentar",
      "id": "TN20NETc1",
      "likes": [],
      "dislikes": [],
      "likesCount": 0,
      "parentCommentId": "xXbMpLzog",
      "postId": null
    }
  ],
  "users": [
    {
      "username": "marko97x",
      "email": "marko97x@gmail.com",
      "password": "marko97x",
      "id": "62Wv5g3xs",
      "comments": [
        "comment1"
      ],
      "posts": [
        "post1"
      ],
      "likedPosts": [
        "post1"
      ],
      "dislikedPosts": [],
      "likedComments": [
        "comment1"
      ],
      "dislikedComments": [
        "l4Q7Einee"
      ]
    },
    {
      "id": "7x25RQ2Sl",
      "username": "marko977x",
      "email": "marko977x@gmail.com",
      "password": "marko977x",
      "posts": [
        "DRK742aPQ"
      ],
      "comments": [],
      "likedPosts": [
        "Si-SCaMro",
        "post1"
      ],
      "dislikedPosts": [],
      "likedComments": [
        "xXbMpLzog",
        "l4Q7Einee"
      ],
      "dislikedComments": [
        "HRTObbfft"
      ]
    },
    {
      "id": "LQpqWgiZG",
      "username": "marko12",
      "email": "marko@gmail.com",
      "password": "marko12",
      "posts": [
        "63UJlnSbI"
      ],
      "comments": [],
      "likedPosts": [
        "63UJlnSbI",
        "Si-SCaMro",
        "post1"
      ],
      "dislikedPosts": [],
      "likedComments": [
        "comment1"
      ],
      "dislikedComments": [
        "HRTObbfft"
      ]
    }
  ],
  "topics": [
    "Sport",
    "Programming",
    "Football",
    "Basketball",
    "Computer Science",
    "Technology",
    "Education",
    "News",
    "Books",
    "Medicine",
    "Web Development",
    "Software Development"
  ]
}